qsome/__init__.py
qsome/cluster_subsystem.py
qsome/cluster_supersystem.py
qsome/comb_diis.py
qsome/custom_pyscf_methods.py
qsome/helpers.py
qsome/inp_reader.py
qsome/molpro_calc.py
qsome/periodic_subsystem.py
qsome/periodic_supersystem.py
qsome/run_embedding.py
qsome/subsystem.py
qsome/supersystem.py
QSoME-0.1.0.dist-info/LICENSE
QSoME-0.1.0.dist-info/METADATA
QSoME-0.1.0.dist-info/WHEEL
QSoME-0.1.0.dist-info/top_level.txt
QSoME-0.1.0.dist-info/RECORD
